__init__.py
dhn_med_py/version.py
dhn_med_py/med_session.py
dhn_med_py/__init__.py
dhn_med_py/medlib_flags.py
dhn_med_py/med_file/dhnmed_file.c
dhn_med_py/med_file/__init__.py
dhn_med_py/med_file/dhnmed_file.h
dhn_med_py/med_file/dhnmed_file.cpython-311-darwin.so
dhn_med_py-2.0.6.dist-info/RECORD
dhn_med_py-2.0.6.dist-info/WHEEL
dhn_med_py-2.0.6.dist-info/top_level.txt
dhn_med_py-2.0.6.dist-info/METADATA
dhn_med_py-2.0.6.dist-info/licenses/LICENSE
