Metadata-Version: 2.4
Name: dhn_med_py
Version: 2.0.6
Summary: DHN-MED-Py is a wrapper library for Multiscale Electrophysiology Data Format developed by Matt Stead.
Author-email:  Jan Cimbalnik <jan.cimbalnik@fnusa.cz>
License: GNU General Public License
Project-URL: homepage, https://github.com/MEDFormat/MEDPython/
Project-URL: repository, https://github.com/MEDFormat/MEDPython/
Keywords: MED,Electrophysiology
Classifier: Intended Audience :: Science/Research
Classifier: License :: OSI Approved :: Apache Software License
Classifier: Operating System :: OS Independent
Classifier: Programming Language :: Python :: 3
Classifier: Programming Language :: Python :: 3 :: Only
Classifier: Programming Language :: Python :: 3.12
Classifier: Programming Language :: Python :: 3.11
Classifier: Programming Language :: Python :: 3.10
Classifier: Programming Language :: Python :: 3.9
Classifier: Topic :: Scientific/Engineering
Requires-Python: >=3.9
License-File: LICENSE
Requires-Dist: numpy
Dynamic: license-file
